llama_index/readers/dashscope/__init__.py
llama_index/readers/dashscope/base.py
llama_index/readers/dashscope/utils.py
llama_index/readers/dashscope/domain/base_domains.py
llama_index/readers/dashscope/domain/lease_domains.py
llama_index_readers_dashscope-0.4.0.dist-info/METADATA
llama_index_readers_dashscope-0.4.0.dist-info/WHEEL
llama_index_readers_dashscope-0.4.0.dist-info/licenses/LICENSE
llama_index_readers_dashscope-0.4.0.dist-info/RECORD
